{
	"_meta":{
		"sources":[
			{
				"json":"urbanLife",
				"abbreviation":"ULTLC",
				"full":"Urban Life: Tables for Living in the City",
				"authors":[
					"Zuishin"
				],
				"convertedBy":"Zuishin",
				"version":"1.0",
				"url":"https://github.com/ZuishinGit/ZuishinHomebrew/tree/master",
				"targetSchema":"1.0.0"
			}
		]
	},
	"book":[
		{
			"name":"Urban Life",
			"id":"ULTLC",
			"source":"urbanLife",
			"contents":[
				{
					"name":"Urban Life",
					"headers":[
						"Per-day living",
						"Food, drink, and lodging",
						"Hiring someone?"
					]
				}
			]
		}
	],
	"bookData":[
		{
			"id":"ULTLC",
			"source":"UL",
			"data":[
				{
					"type":"section",
					"name":"Urban Life",
					"entries":[
						{
							"type":"section",
							"name":"Per-day living",
							"entries":[
								{
									"type":"table",
									"caption":"Lfestyle Expenses",
									"colLabels":[
										"Lifestyle",
										"Price/Day"
									],
									"colStyles":[
										"col-4",
										"col-4 text-right"
									],
									"rows":[
										[
											"Wretched",
											"-"
										],
										[
											"Squalid",
											"1 sp"
										],
										[
											"Poor",
											"2 sp"
										],
										[
											"Modest",
											"1 gp"
										],
										[
											"Comfortable",
											"2 gp"
										],
										[
											"Wealthy",
											"4 gp"
										],
										[
											"Aristocratic",
											"10 gp minimum"
										]
									]

								}
							]
						},
						{
							"type":"section",
							"name":"Food, drink, and lodging",
							"entries":[
								{
									"type":"table",
									"caption": "Food, Drink, and Lodging",
									"colLabels": [
										"Item",
										"Cost"
									],
									"colStyles": [
										"col-6",
										"col-6 text-right"
									],
									"rows": [
										[
											"{@i Ale}",
											""
										],
										{
											"type": "row",
											"style": "row-indent-first",
											"row": [
												"{@item Ale (Gallon)|PHB|Gallon}",
												"2 sp"
											]
										},
										{
											"type": "row",
											"style": "row-indent-first",
											"row": [
												"{@item Ale (mug)|phb|Mug}",
												"4 cp"
											]
										},
										[
											"Banquet (per person)",
											"10 gp"
										],
										[
											"{@item loaf of bread|phb|Bread, loaf}",
											"2 cp"
										],
										[
											"{@item hunk of cheese|phb|Cheese, hunk}",
											"1 sp"
										],
										[
											"{@i Inn stay (per day)}",
											""
										],
										{
											"type": "row",
											"style": "row-indent-first",
											"row": [
												"Squalid",
												"7 cp"
											]
										},
										{
											"type": "row",
											"style": "row-indent-first",
											"row": [
												"Poor",
												"1 sp"
											]
										},
										{
											"type": "row",
											"style": "row-indent-first",
											"row": [
												"Modest",
												"5 sp"
											]
										},
										{
											"type": "row",
											"style": "row-indent-first",
											"row": [
												"Comfortable",
												"8 sp"
											]
										},
										{
											"type": "row",
											"style": "row-indent-first",
											"row": [
												"Wealthy",
												"2 gp"
											]
										},
										{
											"type": "row",
											"style": "row-indent-first",
											"row": [
												"Aristocratic",
												"4 gp"
											]
										},
										[
											"{@i Meals (per day)}",
											""
										],
										{
											"type": "row",
											"style": "row-indent-first",
											"row": [
												"Squalid",
												"3 cp"
											]
										},
										{
											"type": "row",
											"style": "row-indent-first",
											"row": [
												"Poor",
												"6 cp"
											]
										},
										{
											"type": "row",
											"style": "row-indent-first",
											"row": [
												"Modest",
												"3 sp"
											]
										},
										{
											"type": "row",
											"style": "row-indent-first",
											"row": [
												"Comfortable",
												"5 sp"
											]
										},
										{
											"type": "row",
											"style": "row-indent-first",
											"row": [
												"Wealthy",
												"8 sp"
											]
										},
										{
											"type": "row",
											"style": "row-indent-first",
											"row": [
												"Aristocratic",
												"2 gp"
											]
										},
										[
											"{@item chunk of meat|phb|Meat, chunk}",
											"3 sp"
										],
										[
											"{@i Wine}",
											""
										],
										{
											"type": "row",
											"style": "row-indent-first",
											"row": [
												"{@item common wine (pitcher)|phb|Common (pitcher)}",
												"2 sp"
											]
										},
										{
											"type": "row",
											"style": "row-indent-first",
											"row": [
												"{@item fine wine (bottle)|phb|Fine (bottle)}",
												"10 gp"
											]
										}
									]

								}
							]
						},
						{
							"type":"section",
							"name":"Hiring someone?",
							"entries":[
								{
									"type":"table",
									"caption": "Services",
									"colLabels": [
										"Service",
										"Pay"
									],
									"colStyles": [
										"col-6",
										"col-6"
									],
									"rows": [
										[
											"{@i Coach cab}",
											""
										],
										{
											"type": "row",
											"style": "row-indent-first",
											"row": [
												"Between towns",
												"3 cp per mile"
											]
										},
										{
											"type": "row",
											"style": "row-indent-first",
											"row": [
												"Coach cab, Within a city",
												"1 cp"
											]
										},
										[
											"{@i Hireling}",
											""
										],
										{
											"type": "row",
											"style": "row-indent-first",
											"row": [
												"Skilled",
												"2 gp per day"
											]
										},
										{
											"type": "row",
											"style": "row-indent-first",
											"row": [
												"Untrained",
												"2 sp per day"
											]
										},
										[
											"Messenger",
											"2 cp per mile"
										],
										[
											"Road or gate toll",
											"1 cp"
										],
										[
											"Ship's passage",
											"1 sp per mile"
										]
									]
								}
							]
						}
					]
				}
			]
		}
	]
}